[{"c":1,"avg":9.13,"min":4.88,"max":17.0,"n":25854},{"c":47,"avg":10.84,"min":3.0,"max":20.0,"n":22305},{"c":69,"avg":13.07,"min":0.13,"max":33.0,"n":8517},{"c":70,"avg":18.26,"min":0.08,"max":39.9,"n":17405},{"c":88,"avg":10.26,"min":3.99,"max":28.0,"n":18323},{"c":92,"avg":13.71,"min":1.3,"max":41.16,"n":26161},{"c":93,"avg":20.59,"min":10.99,"max":38.0,"n":12614},{"c":95,"avg":9.71,"min":3.5,"max":22.2,"n":35644},{"c":96,"avg":10.08,"min":0.1,"max":36.99,"n":28757},{"c":97,"avg":14.48,"min":1.7,"max":35.0,"n":28085},{"c":98,"avg":10.21,"min":2.0,"max":22.0,"n":28594},{"c":104,"avg":3.39,"min":0.29,"max":12.8,"n":25574},{"c":108,"avg":10.02,"min":0.85,"max":31.25,"n":30973},{"c":109,"avg":4.44,"min":0.2,"max":600.0,"n":34244},{"c":113,"avg":3.76,"min":0.5,"max":400.0,"n":34230},{"c":114,"avg":7.29,"min":0.79,"max":1000.0,"n":33285},{"c":129,"avg":3.75,"min":0.03,"max":11.98,"n":35863},{"c":845,"avg":36.94,"min":2.6,"max":69.9,"n":18316},{"c":1111,"avg":12.84,"min":0.6,"max":18.5,"n":19356},{"c":1131,"avg":3.14,"min":0.9,"max":7.98,"n":31358},{"c":1132,"avg":7.67,"min":0.79,"max":19.6,"n":29527},{"c":1436,"avg":16.29,"min":1.9,"max":29.9,"n":18749},{"c":1441,"avg":2.81,"min":0.28,"max":9.9,"n":7374},{"c":1442,"avg":4.37,"min":1.59,"max":25.8,"n":19631},{"c":1458,"avg":5.19,"min":0.5,"max":12.0,"n":29052},{"c":1481,"avg":8.99,"min":0.13,"max":25.35,"n":31869},{"c":1555,"avg":34.37,"min":8.99,"max":69.9,"n":22411},{"c":1558,"avg":6.07,"min":0.8,"max":46.91,"n":28062},{"c":1560,"avg":8.56,"min":0.79,"max":27.5,"n":19491},{"c":1564,"avg":9.48,"min":0.99,"max":20.0,"n":34974},{"c":1819,"avg":10.2,"min":0.5,"max":900.0,"n":30518},{"c":1916,"avg":29.65,"min":10.99,"max":46.9,"n":6371},{"c":1926,"avg":15.89,"min":6.0,"max":60.0,"n":27118},{"c":1927,"avg":32.33,"min":2.25,"max":72.0,"n":23287},{"c":1928,"avg":6.34,"min":1.0,"max":20.0,"n":31305},{"c":2047,"avg":13.68,"min":3.0,"max":30.9,"n":23013},{"c":2087,"avg":6.24,"min":0.58,"max":14.2,"n":28828},{"c":94,"avg":20.48,"min":8.0,"max":48.9,"n":20861},{"c":131,"avg":12.3,"min":2.29,"max":27.79,"n":17240},{"c":1109,"avg":13.91,"min":4.9,"max":23.3,"n":19017},{"c":1110,"avg":13.39,"min":1.26,"max":20.0,"n":22241},{"c":1440,"avg":3.62,"min":0.99,"max":12.0,"n":25513},{"c":1475,"avg":55.85,"min":5.0,"max":130.0,"n":2992},{"c":1476,"avg":17.11,"min":5.98,"max":30.0,"n":12422},{"c":1477,"avg":19.66,"min":1.7,"max":33.0,"n":11402},{"c":1556,"avg":6.2,"min":0.98,"max":26.0,"n":21138},{"c":1559,"avg":5.93,"min":0.99,"max":22.9,"n":23777},{"c":1921,"avg":16.92,"min":4.99,"max":29.99,"n":17508},{"c":2045,"avg":13.19,"min":1.4,"max":29.9,"n":22421},{"c":2086,"avg":6.88,"min":0.5,"max":1000.0,"n":25395},{"c":847,"avg":36.95,"min":3.6,"max":65.9,"n":12080},{"c":105,"avg":6.37,"min":0.98,"max":12.99,"n":14419},{"c":2107,"avg":3.33,"min":0.99,"max":7.5,"n":2508},{"c":132,"avg":12.91,"min":1.39,"max":26.0,"n":8938},{"c":861,"avg":4.13,"min":1.49,"max":11.11,"n":3033},{"c":2,"avg":11.33,"min":2.9,"max":18.99,"n":7859},{"c":55,"avg":15.12,"min":1.9,"max":24.9,"n":11562},{"c":1931,"avg":3.12,"min":1.5,"max":10.9,"n":1601},{"c":1443,"avg":6.55,"min":1.79,"max":15.0,"n":664},{"c":1444,"avg":4.92,"min":1.89,"max":8.5,"n":123},{"c":904,"avg":36.57,"min":20.99,"max":46.19,"n":2045},{"c":1583,"avg":33.29,"min":28.8,"max":42.5,"n":827},{"c":2066,"avg":33.91,"min":4.49,"max":48.0,"n":3692},{"c":2068,"avg":36.6,"min":31.5,"max":49.9,"n":3139},{"c":9,"avg":33.34,"min":22.9,"max":60.9,"n":910},{"c":43,"avg":26.9,"min":10.9,"max":56.0,"n":3457},{"c":350,"avg":6.37,"min":4.0,"max":649.0,"n":9092},{"c":883,"avg":4.26,"min":2.78,"max":6.0,"n":6353},{"c":917,"avg":3.29,"min":2.15,"max":4.5,"n":7373},{"c":1128,"avg":14.58,"min":5.9,"max":33.5,"n":5252},{"c":1367,"avg":37.02,"min":27.88,"max":47.99,"n":285},{"c":1379,"avg":42.98,"min":22.0,"max":89.9,"n":491},{"c":1380,"avg":33.25,"min":20.0,"max":59.0,"n":320},{"c":1431,"avg":35.52,"min":25.0,"max":160.11,"n":486},{"c":1432,"avg":34.93,"min":23.0,"max":46.0,"n":466},{"c":1479,"avg":12.74,"min":3.99,"max":26.9,"n":3872},{"c":1483,"avg":1.79,"min":0.98,"max":16.99,"n":6365},{"c":1550,"avg":15.0,"min":8.49,"max":27.99,"n":3546},{"c":1551,"avg":13.69,"min":8.88,"max":20.9,"n":3016},{"c":1552,"avg":11.97,"min":6.99,"max":23.2,"n":2231},{"c":1553,"avg":14.73,"min":9.99,"max":25.99,"n":4861},{"c":1572,"avg":6.3,"min":0.6,"max":8.2,"n":9187},{"c":1584,"avg":3.12,"min":1.85,"max":29.99,"n":7013},{"c":1611,"avg":4.08,"min":2.99,"max":5.5,"n":8369},{"c":1804,"avg":15.6,"min":7.59,"max":25.99,"n":5269},{"c":1899,"avg":20.28,"min":10.4,"max":40.0,"n":6051},{"c":1919,"avg":60.94,"min":17.99,"max":109.9,"n":102},{"c":1976,"avg":5.27,"min":1.9,"max":458.0,"n":8754},{"c":102,"avg":12.2,"min":7.5,"max":20.0,"n":1018},{"c":191,"avg":10.39,"min":7.5,"max":13.3,"n":8063},{"c":217,"avg":4.23,"min":1.99,"max":42.0,"n":7524},{"c":254,"avg":35.74,"min":24.88,"max":45.9,"n":4434},{"c":260,"avg":35.05,"min":6.9,"max":44.9,"n":5059},{"c":364,"avg":7.71,"min":5.5,"max":9.99,"n":8493},{"c":368,"avg":9.52,"min":5.0,"max":25.9,"n":7252},{"c":716,"avg":32.0,"min":7.7,"max":59.99,"n":1395},{"c":850,"avg":45.71,"min":28.9,"max":89.0,"n":972},{"c":918,"avg":2.51,"min":2.49,"max":25.0,"n":3021},{"c":929,"avg":23.89,"min":2.99,"max":33.2,"n":2297},{"c":1070,"avg":4.34,"min":1.99,"max":6.8,"n":8255},{"c":1138,"avg":5.86,"min":4.2,"max":8.0,"n":7668},{"c":1437,"avg":21.24,"min":8.99,"max":39.0,"n":2908},{"c":1568,"avg":6.82,"min":4.88,"max":695.0,"n":7522},{"c":1570,"avg":6.68,"min":4.59,"max":10.5,"n":7940},{"c":1577,"avg":9.2,"min":6.3,"max":12.0,"n":7251},{"c":1585,"avg":3.78,"min":2.2,"max":5.75,"n":6144},{"c":1589,"avg":2.88,"min":2.5,"max":285.0,"n":9101},{"c":1929,"avg":15.69,"min":2.0,"max":28.0,"n":760},{"c":2114,"avg":20.74,"min":13.38,"max":31.9,"n":3146},{"c":10,"avg":34.03,"min":30.0,"max":40.0,"n":60},{"c":11,"avg":45.39,"min":34.2,"max":57.69,"n":151},{"c":12,"avg":44.39,"min":35.0,"max":50.0,"n":31},{"c":14,"avg":24.1,"min":18.99,"max":35.0,"n":1303},{"c":101,"avg":3.43,"min":1.5,"max":38.0,"n":1416},{"c":103,"avg":11.08,"min":4.5,"max":20.0,"n":1452},{"c":206,"avg":11.45,"min":5.5,"max":15.9,"n":5039},{"c":214,"avg":6.84,"min":5.0,"max":10.0,"n":7936},{"c":218,"avg":4.59,"min":3.2,"max":7.3,"n":5718},{"c":910,"avg":12.11,"min":9.45,"max":15.9,"n":2132},{"c":1151,"avg":16.37,"min":4.5,"max":19.9,"n":7535},{"c":1368,"avg":37.86,"min":32.5,"max":40.0,"n":62},{"c":1375,"avg":23.0,"min":2.0,"max":30.0,"n":768},{"c":1376,"avg":22.81,"min":18.49,"max":28.0,"n":359},{"c":1377,"avg":23.77,"min":17.69,"max":31.8,"n":931},{"c":1422,"avg":5.41,"min":0.5,"max":15.0,"n":5484},{"c":1554,"avg":55.92,"min":4.0,"max":109.9,"n":1891},{"c":1900,"avg":20.75,"min":11.9,"max":50.0,"n":2523},{"c":1914,"avg":23.75,"min":17.99,"max":70.9,"n":1237},{"c":1915,"avg":49.89,"min":20.0,"max":99.9,"n":1982},{"c":1953,"avg":3.45,"min":2.79,"max":4.9,"n":5287},{"c":2056,"avg":4.07,"min":3.0,"max":7.9,"n":2829},{"c":2111,"avg":14.89,"min":11.85,"max":23.99,"n":2520},{"c":2112,"avg":6.46,"min":0.59,"max":9.9,"n":3307},{"c":2113,"avg":14.02,"min":1.28,"max":17.99,"n":3124},{"c":365,"avg":7.28,"min":5.0,"max":79.77,"n":6469},{"c":1438,"avg":48.44,"min":16.0,"max":85.9,"n":1955},{"c":1923,"avg":9.72,"min":2.79,"max":18.99,"n":3825},{"c":1937,"avg":6.91,"min":4.99,"max":29.95,"n":2832},{"c":1938,"avg":13.25,"min":10.0,"max":30.9,"n":3920},{"c":1939,"avg":30.64,"min":13.3,"max":31.88,"n":4740},{"c":180,"avg":14.13,"min":1.0,"max":18.5,"n":1984},{"c":263,"avg":30.21,"min":23.38,"max":33.49,"n":5843},{"c":1093,"avg":8.65,"min":6.9,"max":10.99,"n":4247},{"c":1094,"avg":7.04,"min":6.5,"max":675.0,"n":4218},{"c":1142,"avg":9.56,"min":5.49,"max":11.9,"n":4520},{"c":1369,"avg":55.92,"min":33.99,"max":65.0,"n":72},{"c":1378,"avg":23.76,"min":19.1,"max":33.4,"n":603},{"c":1391,"avg":41.82,"min":6.59,"max":88.9,"n":153},{"c":1600,"avg":16.16,"min":7.15,"max":38.9,"n":4643},{"c":1601,"avg":13.14,"min":6.9,"max":18.3,"n":5085},{"c":1650,"avg":15.83,"min":9.99,"max":20.9,"n":2093},{"c":2025,"avg":18.73,"min":13.9,"max":23.9,"n":5795},{"c":2115,"avg":19.49,"min":13.2,"max":25.5,"n":2024},{"c":2110,"avg":22.69,"min":12.99,"max":34.5,"n":2387},{"c":1095,"avg":30.77,"min":3.9,"max":39.9,"n":4000},{"c":1598,"avg":16.32,"min":11.88,"max":35.9,"n":4220},{"c":1602,"avg":13.26,"min":3.3,"max":30.0,"n":3214},{"c":1612,"avg":3.96,"min":3.2,"max":4.8,"n":2469},{"c":1870,"avg":3.65,"min":2.5,"max":5.0,"n":3167},{"c":1101,"avg":13.22,"min":9.1,"max":30.9,"n":5265},{"c":1396,"avg":4.05,"min":1.69,"max":5.0,"n":59},{"c":16,"avg":6.79,"min":2.99,"max":690.0,"n":1055},{"c":21,"avg":3.84,"min":1.68,"max":6.99,"n":1134},{"c":24,"avg":6.8,"min":3.48,"max":10.99,"n":853},{"c":25,"avg":4.6,"min":2.0,"max":8.9,"n":986},{"c":52,"avg":25.29,"min":12.9,"max":65.8,"n":995},{"c":64,"avg":29.15,"min":10.99,"max":50.0,"n":850},{"c":193,"avg":9.32,"min":0.59,"max":12.1,"n":4709},{"c":201,"avg":9.37,"min":8.1,"max":10.5,"n":2121},{"c":203,"avg":12.79,"min":5.9,"max":1260.0,"n":3150},{"c":205,"avg":9.51,"min":4.2,"max":13.2,"n":4978},{"c":224,"avg":8.66,"min":7.0,"max":11.0,"n":1087},{"c":228,"avg":3.86,"min":2.3,"max":5.0,"n":2659},{"c":229,"avg":1.74,"min":0.1,"max":15.0,"n":2301},{"c":230,"avg":3.45,"min":1.99,"max":4.5,"n":2830},{"c":232,"avg":3.01,"min":1.29,"max":4.99,"n":2720},{"c":235,"avg":6.76,"min":0.6,"max":8.8,"n":3124},{"c":239,"avg":2.46,"min":0.99,"max":4.25,"n":2095},{"c":240,"avg":2.21,"min":1.75,"max":4.29,"n":983},{"c":246,"avg":18.7,"min":8.88,"max":21.99,"n":1742},{"c":266,"avg":30.68,"min":20.4,"max":30.99,"n":5679},{"c":267,"avg":6.89,"min":6.5,"max":6.9,"n":3124},{"c":271,"avg":34.75,"min":25.95,"max":43.5,"n":892},{"c":293,"avg":14.36,"min":5.95,"max":16.8,"n":3136},{"c":299,"avg":28.82,"min":2.9,"max":55.5,"n":6048},{"c":300,"avg":28.81,"min":23.99,"max":32.0,"n":5919},{"c":884,"avg":3.43,"min":2.69,"max":5.89,"n":3836},{"c":1086,"avg":16.23,"min":5.19,"max":19.9,"n":3135},{"c":1087,"avg":41.53,"min":29.9,"max":48.9,"n":2629},{"c":1088,"avg":47.5,"min":38.88,"max":52.0,"n":1073},{"c":1089,"avg":43.35,"min":32.88,"max":62.6,"n":982},{"c":1090,"avg":15.8,"min":12.49,"max":22.2,"n":1595},{"c":1100,"avg":6.89,"min":6.69,"max":13.3,"n":2454},{"c":1135,"avg":5.2,"min":3.75,"max":9.5,"n":5217},{"c":1144,"avg":15.42,"min":11.8,"max":1418.0,"n":2752},{"c":1145,"avg":17.03,"min":8.9,"max":20.9,"n":5729},{"c":1153,"avg":2.38,"min":0.24,"max":3.9,"n":2645},{"c":1355,"avg":3.63,"min":1.8,"max":4.99,"n":3101},{"c":1489,"avg":1.47,"min":0.99,"max":5.5,"n":2757},{"c":1507,"avg":1.96,"min":1.2,"max":3.0,"n":2837},{"c":1515,"avg":8.87,"min":5.0,"max":11.49,"n":1111},{"c":1517,"avg":7.66,"min":4.6,"max":8.9,"n":649},{"c":1544,"avg":1.42,"min":0.95,"max":3.4,"n":2827},{"c":1545,"avg":1.42,"min":0.99,"max":1.9,"n":2512},{"c":1547,"avg":1.81,"min":0.99,"max":2.89,"n":2596},{"c":1562,"avg":7.99,"min":3.5,"max":19.5,"n":2162},{"c":1563,"avg":99.79,"min":7.49,"max":278.6,"n":584},{"c":1588,"avg":3.49,"min":0.9,"max":5.8,"n":1915},{"c":1590,"avg":2.95,"min":2.85,"max":3.95,"n":2805},{"c":1595,"avg":29.24,"min":23.6,"max":34.6,"n":2641},{"c":1603,"avg":18.22,"min":13.59,"max":25.9,"n":2719},{"c":1604,"avg":4.97,"min":1.65,"max":6.5,"n":2982},{"c":1606,"avg":17.14,"min":12.88,"max":21.9,"n":2730},{"c":1610,"avg":8.32,"min":0.83,"max":16.5,"n":3511},{"c":1613,"avg":2.8,"min":2.25,"max":4.5,"n":3178},{"c":1615,"avg":14.87,"min":11.58,"max":18.5,"n":3179},{"c":1619,"avg":19.92,"min":15.99,"max":22.45,"n":2164},{"c":1628,"avg":9.96,"min":1.1,"max":15.5,"n":5841},{"c":1635,"avg":9.93,"min":7.49,"max":11.9,"n":2635},{"c":1849,"avg":5.04,"min":0.4,"max":7.9,"n":2311},{"c":1872,"avg":7.96,"min":3.9,"max":9.9,"n":2664},{"c":1876,"avg":12.89,"min":9.9,"max":40.9,"n":2185},{"c":1879,"avg":1.81,"min":0.15,"max":2.5,"n":2471},{"c":1904,"avg":26.75,"min":20.88,"max":35.25,"n":6528},{"c":1944,"avg":8.11,"min":3.45,"max":20.0,"n":2259},{"c":1955,"avg":2.82,"min":1.5,"max":3.8,"n":2543},{"c":1963,"avg":36.08,"min":3.75,"max":67.9,"n":2137},{"c":1964,"avg":11.49,"min":8.8,"max":15.09,"n":358},{"c":1966,"avg":7.72,"min":5.57,"max":10.0,"n":3341},{"c":1987,"avg":19.3,"min":12.88,"max":24.25,"n":1856},{"c":1988,"avg":19.97,"min":6.9,"max":23.6,"n":1936},{"c":1989,"avg":10.96,"min":4.89,"max":16.8,"n":1876},{"c":1990,"avg":11.38,"min":5.8,"max":15.88,"n":1037},{"c":1999,"avg":13.59,"min":4.9,"max":17.8,"n":2837},{"c":2000,"avg":14.34,"min":8.88,"max":17.9,"n":3054},{"c":2001,"avg":29.6,"min":25.5,"max":39.5,"n":5607},{"c":2009,"avg":25.23,"min":18.99,"max":84.65,"n":7218},{"c":2010,"avg":25.15,"min":18.99,"max":55.75,"n":7173},{"c":2011,"avg":3.27,"min":1.19,"max":3.99,"n":3108},{"c":2014,"avg":57.16,"min":40.2,"max":70.95,"n":3099},{"c":2020,"avg":2.88,"min":2.25,"max":5.8,"n":2711},{"c":2022,"avg":7.74,"min":4.9,"max":10.29,"n":5411},{"c":2023,"avg":16.42,"min":12.98,"max":20.39,"n":1915},{"c":2027,"avg":73.16,"min":7.32,"max":80.29,"n":1644},{"c":2030,"avg":68.83,"min":62.99,"max":75.7,"n":1480},{"c":2031,"avg":64.21,"min":19.9,"max":79.1,"n":3304},{"c":2053,"avg":11.84,"min":7.88,"max":17.0,"n":3209},{"c":2057,"avg":6.02,"min":3.85,"max":7.99,"n":3609},{"c":2059,"avg":8.52,"min":5.5,"max":11.8,"n":3328},{"c":2060,"avg":8.51,"min":6.7,"max":10.9,"n":1676},{"c":2062,"avg":78.78,"min":41.0,"max":88.8,"n":3525},{"c":2089,"avg":9.9,"min":8.35,"max":16.2,"n":2930},{"c":2090,"avg":5.81,"min":4.88,"max":56.9,"n":2496},{"c":2094,"avg":6.76,"min":4.49,"max":9.5,"n":3421},{"c":2095,"avg":14.37,"min":1.6,"max":22.25,"n":2952},{"c":2098,"avg":32.93,"min":3.04,"max":55.9,"n":5740},{"c":2100,"avg":31.14,"min":24.8,"max":50.4,"n":5763},{"c":2101,"avg":30.03,"min":2.69,"max":55.99,"n":5484},{"c":2102,"avg":19.14,"min":12.99,"max":28.9,"n":2496},{"c":2103,"avg":20.44,"min":8.9,"max":34.55,"n":2252},{"c":2104,"avg":23.09,"min":17.99,"max":34.95,"n":5328},{"c":2105,"avg":23.05,"min":17.99,"max":31.0,"n":5539},{"c":2106,"avg":19.06,"min":13.5,"max":27.95,"n":1702},{"c":2108,"avg":19.64,"min":13.49,"max":31.8,"n":1804},{"c":2109,"avg":15.18,"min":6.9,"max":21.9,"n":2537},{"c":2099,"avg":32.16,"min":3.5,"max":48.6,"n":3566},{"c":292,"avg":13.98,"min":4.9,"max":16.9,"n":2922},{"c":295,"avg":6.29,"min":3.9,"max":7.99,"n":2095},{"c":1091,"avg":8.55,"min":7.85,"max":15.9,"n":3320},{"c":1524,"avg":4.41,"min":2.0,"max":6.5,"n":2363},{"c":1525,"avg":4.95,"min":2.5,"max":5.99,"n":931},{"c":1605,"avg":1.06,"min":0.5,"max":2.99,"n":2557},{"c":1630,"avg":4.9,"min":2.5,"max":6.9,"n":2131},{"c":1942,"avg":30.64,"min":4.5,"max":30.9,"n":662},{"c":1960,"avg":9.18,"min":7.49,"max":12.9,"n":1609},{"c":1984,"avg":16.5,"min":9.9,"max":24.5,"n":2782},{"c":1992,"avg":10.79,"min":2.7,"max":12.9,"n":1642},{"c":2002,"avg":5.02,"min":3.89,"max":10.69,"n":2770},{"c":2019,"avg":15.15,"min":8.69,"max":20.2,"n":3391},{"c":2091,"avg":2.52,"min":1.78,"max":3.9,"n":2112},{"c":2092,"avg":5.74,"min":4.9,"max":7.9,"n":1908},{"c":1998,"avg":23.94,"min":6.8,"max":28.35,"n":624},{"c":2032,"avg":30.26,"min":24.9,"max":42.9,"n":1952},{"c":2093,"avg":6.35,"min":4.5,"max":9.8,"n":1566},{"c":2096,"avg":6.18,"min":4.98,"max":8.5,"n":1758},{"c":18,"avg":7.3,"min":4.65,"max":9.9,"n":737},{"c":39,"avg":10.36,"min":3.5,"max":17.99,"n":543},{"c":1597,"avg":29.92,"min":24.88,"max":44.19,"n":938},{"c":2042,"avg":28.98,"min":0.28,"max":36.5,"n":1632},{"c":19,"avg":7.4,"min":3.9,"max":9.2,"n":384},{"c":20,"avg":5.29,"min":1.87,"max":8.3,"n":739},{"c":22,"avg":10.14,"min":4.88,"max":20.9,"n":887},{"c":27,"avg":11.71,"min":5.88,"max":29.99,"n":1405},{"c":38,"avg":7.53,"min":3.88,"max":20.9,"n":729},{"c":869,"avg":1.49,"min":0.59,"max":5.0,"n":1806},{"c":1940,"avg":6.9,"min":6.69,"max":7.9,"n":264},{"c":1947,"avg":6.36,"min":2.39,"max":7.5,"n":2012},{"c":1539,"avg":2.72,"min":2.2,"max":5.5,"n":2180},{"c":849,"avg":20.38,"min":10.0,"max":35.9,"n":597},{"c":1913,"avg":32.94,"min":24.5,"max":58.9,"n":107},{"c":1596,"avg":29.27,"min":20.1,"max":32.2,"n":131},{"c":1825,"avg":28.68,"min":27.9,"max":30.0,"n":660},{"c":1826,"avg":28.47,"min":27.0,"max":31.0,"n":612},{"c":2004,"avg":27.2,"min":27.2,"max":27.2,"n":4},{"c":2036,"avg":3.33,"min":2.95,"max":4.2,"n":21},{"c":2048,"avg":3.18,"min":2.59,"max":3.4,"n":18},{"c":1854,"avg":12.63,"min":9.5,"max":15.4,"n":509},{"c":1951,"avg":29.68,"min":3.4,"max":32.0,"n":653},{"c":1373,"avg":47.98,"min":22.9,"max":59.99,"n":97},{"c":1491,"avg":8.46,"min":6.05,"max":9.8,"n":29},{"c":1492,"avg":7.5,"min":6.05,"max":8.19,"n":32},{"c":1941,"avg":13.24,"min":9.99,"max":13.3,"n":257},{"c":31,"avg":2.06,"min":0.96,"max":12.99,"n":401},{"c":1832,"avg":28.04,"min":26.88,"max":29.5,"n":139},{"c":1833,"avg":30.65,"min":28.69,"max":32.5,"n":575},{"c":1371,"avg":47.56,"min":34.99,"max":75.9,"n":96},{"c":2003,"avg":4.36,"min":1.25,"max":7.5,"n":594},{"c":1823,"avg":34.55,"min":33.0,"max":39.0,"n":194},{"c":1824,"avg":33.16,"min":3.38,"max":36.0,"n":165},{"c":1827,"avg":3.38,"min":2.5,"max":4.5,"n":477},{"c":1852,"avg":7.61,"min":6.9,"max":8.9,"n":75},{"c":1822,"avg":28.09,"min":26.9,"max":29.5,"n":152},{"c":226,"avg":1.2,"min":0.9,"max":1.5,"n":177},{"c":1651,"avg":1.21,"min":0.9,"max":1.6,"n":225},{"c":1370,"avg":48.47,"min":19.99,"max":75.9,"n":65},{"c":1400,"avg":13.21,"min":8.9,"max":18.0,"n":23},{"c":1412,"avg":4.68,"min":2.49,"max":10.59,"n":33},{"c":221,"avg":1.16,"min":1.0,"max":2.75,"n":119},{"c":118,"avg":4.78,"min":4.7,"max":5.0,"n":4},{"c":119,"avg":4.46,"min":4.3,"max":4.8,"n":9},{"c":120,"avg":4.48,"min":4.4,"max":4.7,"n":5},{"c":26,"avg":22.06,"min":9.5,"max":35.8,"n":15},{"c":2035,"avg":19.62,"min":18.5,"max":20.3,"n":20},{"c":1372,"avg":48.1,"min":31.5,"max":79.9,"n":49},{"c":1581,"avg":28.99,"min":26.0,"max":36.9,"n":7},{"c":1582,"avg":26.0,"min":26.0,"max":26.0,"n":5},{"c":1445,"avg":27.36,"min":7.19,"max":35.95,"n":5},{"c":2097,"avg":39.26,"min":38.5,"max":39.7,"n":10},{"c":992,"avg":34.39,"min":33.8,"max":34.99,"n":2},{"c":1420,"avg":18.74,"min":15.9,"max":19.6,"n":5},{"c":1419,"avg":13.74,"min":13.5,"max":13.9,"n":5},{"c":1399,"avg":9.99,"min":9.99,"max":9.99,"n":1},{"c":2037,"avg":4.8,"min":4.8,"max":4.8,"n":2}]